pecanpy/__init__.py
pecanpy/cli.py
pecanpy/experimental.py
pecanpy/graph.py
pecanpy/pecanpy.py
pecanpy/typing.py
pecanpy/wrappers.py
pecanpy/rw/__init__.py
pecanpy/rw/dense_rw.py
pecanpy/rw/sparse_rw.py
pecanpy-2.0.9.dist-info/METADATA
pecanpy-2.0.9.dist-info/WHEEL
pecanpy-2.0.9.dist-info/entry_points.txt
pecanpy-2.0.9.dist-info/top_level.txt
pecanpy-2.0.9.dist-info/RECORD
