Metadata-Version: 2.1
Name: pecanpy
Version: 2.0.9
Summary: A parallelized, efficient, and accelerated node2vec
Home-page: https://github.com/krishnanlab/PecanPy
Author: Remy Liu
Author-email: liurenmi@msu.edu
License: BSD 3-Clause License
Project-URL: Documentation, https://pecanpy.readthedocs.io/
Keywords: Network Embedding
Classifier: Development Status :: 5 - Production/Stable
Classifier: Programming Language :: Python
Classifier: Programming Language :: Python :: 3 :: Only
Classifier: Programming Language :: Python :: 3.8
Classifier: Programming Language :: Python :: 3.9
Requires-Python: >=3.8
Requires-Dist: gensim >=4.1.0
Requires-Dist: numpy >=1.20.0
Requires-Dist: numba >=0.46.0
Requires-Dist: numba-progress >=0.0.2
Requires-Dist: nptyping >=2.0.0
Requires-Dist: typing-extensions >=4.0.1
Provides-Extra: dev
Requires-Dist: bump2version ==1.0.1 ; extra == 'dev'
Requires-Dist: mypy ==1.8.0 ; extra == 'dev'
Requires-Dist: parameterized ==0.9.0 ; extra == 'dev'
Requires-Dist: pytest-cov ==4.1.0 ; extra == 'dev'
Requires-Dist: pytest-xdist ==3.5.0 ; extra == 'dev'
Requires-Dist: pytest ==7.4.4 ; extra == 'dev'
Requires-Dist: tox ==4.11.4 ; extra == 'dev'
Requires-Dist: pre-commit ==3.5.0 ; (python_version < "3.9") and extra == 'dev'
Requires-Dist: pre-commit ==3.6.0 ; (python_version >= "3.9") and extra == 'dev'
